panclus/Panclus.py
panclus/__init__.py
panclus-1.3.3.data/scripts/Panclus.py
panclus-1.3.3.data/scripts/__init__.py
panclus-1.3.3.dist-info/LICENSE.txt
panclus-1.3.3.dist-info/METADATA
panclus-1.3.3.dist-info/WHEEL
panclus-1.3.3.dist-info/top_level.txt
panclus-1.3.3.dist-info/RECORD
