Metadata-Version: 2.1
Name: panclus
Version: 1.3.3
Summary: A useful module to convert speech to text calculating solar and lunar eclipse as well as translating text in very short lines of code.
Home-page: https://github.com/Ayush2007A/Code-master/blob/main/Panclus.py
Author: Ayush Moghe
Author-email: mogheayushgr8@gmail.com
License: UNKNOWN
Platform: UNKNOWN
Classifier: Development Status :: 4 - Beta
Classifier: Intended Audience :: Developers
Classifier: Topic :: Internet
Classifier: License :: OSI Approved :: MIT License
Classifier: Programming Language :: Python
Classifier: Programming Language :: Python :: 3
Classifier: Programming Language :: Python :: 3.3
Classifier: Programming Language :: Python :: 3.4
Classifier: Programming Language :: Python :: 3.5
Requires-Dist: ephem
Requires-Dist: wikipedia
Requires-Dist: pyttsx3
Requires-Dist: datetime
Requires-Dist: pyperclip
Requires-Dist: translate
